<?xml version="0.25" encoding="utf-8"?>
<TextureAtlas imagePath="phtchica.png">
	<!-- Created with Adobe Animate version 20.5.1.31044 -->
	<!-- http://www.adobe.com/products/animate.html -->
	<SubTexture name="idle0000" x="0" y="0" width="78.75" height="163.25" frameX="-19" frameY="-6.25" frameWidth="110.75" frameHeight="173.75"/>
	<SubTexture name="idle0001" x="79" y="0" width="73.75" height="164.25" frameX="-19" frameY="-5" frameWidth="110.75" frameHeight="173.75"/>
	<SubTexture name="idle0002" x="153" y="0" width="65" height="167" frameX="-19" frameY="-3.25" frameWidth="110.75" frameHeight="173.75"/>
	<SubTexture name="idle0003" x="218.25" y="0" width="66.75" height="169.75" frameX="-19" frameY="-1.25" frameWidth="110.75" frameHeight="173.75"/>
	<SubTexture name="idle0004" x="285.25" y="0" width="70.75" height="171.75" frameX="-19" frameY="0" frameWidth="110.75" frameHeight="173.75"/>
	<SubTexture name="idle0005" x="356.25" y="0" width="74" height="171.5" frameX="-19" frameY="-0.5" frameWidth="110.75" frameHeight="173.75"/>
	<SubTexture name="idle0006" x="430.5" y="0" width="90" height="170.5" frameX="-6" frameY="-2" frameWidth="110.75" frameHeight="173.75"/>
	<SubTexture name="idle0007" x="520.75" y="0" width="99" height="168.75" frameX="0" frameY="-4" frameWidth="110.75" frameHeight="173.75"/>
	<SubTexture name="idle0008" x="620" y="0" width="99.25" height="168" frameX="-3.25" frameY="-5.25" frameWidth="110.75" frameHeight="173.75"/>
	<SubTexture name="idle0009" x="719.5" y="0" width="98.5" height="167.25" frameX="-7.75" frameY="-6.25" frameWidth="110.75" frameHeight="173.75"/>
	<SubTexture name="idle0010" x="818.25" y="0" width="97" height="166.5" frameX="-12.5" frameY="-7" frameWidth="110.75" frameHeight="173.75"/>
	<SubTexture name="idle0011" x="915.5" y="0" width="93.5" height="165.75" frameX="-17.25" frameY="-7.25" frameWidth="110.75" frameHeight="173.75"/>
	<SubTexture name="idle0012" x="0" y="172" width="89.75" height="163.75" frameX="-19" frameY="-6.5" frameWidth="110.75" frameHeight="173.75"/>
	<SubTexture name="idle0013" x="90" y="172" width="86.75" height="161.5" frameX="-19" frameY="-5.75" frameWidth="110.75" frameHeight="173.75"/>
	<SubTexture name="idle0014" x="177" y="172" width="82.75" height="162.75" frameX="-19" frameY="-4.75" frameWidth="110.75" frameHeight="173.75"/>
	<SubTexture name="idle0015" x="260" y="172" width="77.5" height="165.75" frameX="-19" frameY="-3.25" frameWidth="110.75" frameHeight="173.75"/>
	<SubTexture name="idle0016" x="337.75" y="172" width="71.25" height="168.5" frameX="-19" frameY="-1.75" frameWidth="110.75" frameHeight="173.75"/>
	<SubTexture name="idle0017" x="409.25" y="172" width="65.25" height="170.5" frameX="-19" frameY="-1" frameWidth="110.75" frameHeight="173.75"/>
	<SubTexture name="idle0018" x="474.75" y="172" width="67.25" height="170.75" frameX="-19" frameY="-1.25" frameWidth="110.75" frameHeight="173.75"/>
	<SubTexture name="idle0019" x="542.25" y="172" width="69" height="169.75" frameX="-19" frameY="-2.5" frameWidth="110.75" frameHeight="173.75"/>
	<SubTexture name="idle0020" x="611.5" y="172" width="80.75" height="169" frameX="-10.75" frameY="-3.75" frameWidth="110.75" frameHeight="173.75"/>
	<SubTexture name="idle0021" x="692.5" y="172" width="83" height="168.25" frameX="-12.25" frameY="-5" frameWidth="110.75" frameHeight="173.75"/>
	<SubTexture name="idle0022" x="775.75" y="172" width="82" height="167" frameX="-16.75" frameY="-6.5" frameWidth="110.75" frameHeight="173.75"/>
	<SubTexture name="idle0023" x="858" y="172" width="83" height="166.25" frameX="-19" frameY="-7.5" frameWidth="110.75" frameHeight="173.75"/>
	<SubTexture name="idle0024" x="941.25" y="172" width="83" height="166" frameX="-19" frameY="-7.75" frameWidth="110.75" frameHeight="173.75"/>
</TextureAtlas>
